{
    "check":{
        "57e3351cda894696294516264fade6e0": "bca66716b9ca2d13a4c28be69b276777",
        "4265a3dd4f6bb8c10dbb723ba32fc8f5": "d1bd83a33f1a841ab7fda32449746cc4"
    },
    "projects": [
        {
            "name": "World of Warcraft - GroupFinder",
            "cType": 2,
            "shortcut": "WGF",
            "type": "PHP Application",
            "version": "2.8",
            "last_update": "17.04.2019",
            "description": "Twitch-Streamer and Players are able to use this tool to set up lists and find partners for their dungeons and events.",
            "repo_link": "https://github.com/Machigatta/discord-embed-generator",
            "hyperlink": "https://wowgroupfinder.com/",
            "downloads": []
        },
        {
            "name": "Twitch Clip Downloader",
            "cType": 1,
            "shortcut": "tcd",
            "type": "C# Application",
            "version": "3.3",
            "last_update": "09.03.2019",
            "description": "Downloads multiple Twitch-Clips based on many different options.",
            "repo_link": "https://github.com/Machigatta/twitch-clip-downloader",
            "downloads": [
                {
                    "version": "3.0",
                    "type": "zip"
                },
                {
                    "version": "3.1",
                    "type": "zip"
                },
                {
                    "version": "3.2",
                    "type": "zip"
                },
                {
                    "version": "3.3",
                    "type": "zip"
                }
            ]
        },
        {
            "name": "return-null",
            "cType": 4,
            "shortcut": "return-null",
            "type": "E-Book",
            "version": "0.1",
            "last_update": "26.09.2018",
            "description": "Starting Projects we won't finish. This E-Book targets the process of starting projects we will be stuck with in our entire career.",
            "repo_link": "https://github.com/Machigatta/return-null",
            "downloads": []
        },
        {
            "name": "Steam Deal Crawler",
            "cType": 1,
            "shortcut": "sdc",
            "type": "Node.js Bot",
            "version": "1.0.5",
            "last_update": "18.01.2018",
            "description": "This nodeJs-Bot is a simple crawler to search through a specific Tag you always wanted to have.<br>This node-js crawler searches through a tag-name and lists every discount with percentage and price. The export of the result is on your side.",
            "repo_link": "https://github.com/Machigatta/steam-deal-crawler",
            "downloads": []
        },
        {
            "name": "Random Trello-Card Picker",
            "cType": 2,
            "shortcut": "rTCD",
            "type": "Ember.js",
            "version": "1.0",
            "last_update": "08.04.2019",
            "description": "Pick a random card out of your Trello-Boards to work on some random projects.",
            "repo_link": "https://github.com/Machigatta/random-trello-card-picker",
            "hyperlink": "https://trello.machigatta.com/",
            "downloads": []
        },
        {
            "name": "Discord Embed Generator",
            "cType": 2,
            "shortcut": "DiscordEGen",
            "type": "Aurelia.js",
            "version": "1.1",
            "last_update": "14.04.2019",
            "description": "Generate some simple embeds to test your discord-webhooks.",
            "repo_link": "https://github.com/Machigatta/discord-embed-generator",
            "hyperlink": "https://embed.machigatta.com/",
            "downloads": []
        },
        {
            "name": "League of Antitilt",
            "cType": 1,
            "shortcut": "loa",
            "type": "C# WPF Application",
            "version": "1.0",
            "last_update": "22.03.2019",
            "description": "Just a little Troll-App to notify yourself after the game startet to 'mute them all'!",
            "repo_link": "https://github.com/Machigatta/league-of-antitilt",
            "downloads": []
        },
        {
            "name": "wshbr-theme",
            "cType": 3,
            "shortcut": "wshbrT",
            "type": "Wordpress Theme",
            "version": "0.7",
            "last_update": "17.03.2019",
            "description": "This is the repository for the main-design for the german news-website https://wshbr.de/",
            "repo_link": "https://github.com/Machigatta/wshbr-wordpress-theme",
            "downloads": []
        },
        {
            "name": "wshbr-wordpress-themoviedb-sidebar",
            "cType": 3,
            "shortcut": "wshbrTMDBs",
            "type": "Wordpress Plugin",
            "version": "1.2",
            "last_update": "17.03.2019",
            "description": "A simple wordpress plugin to grab information for a movie or series from https://www.themoviedb.org into a sidebar",
            "repo_link": "https://github.com/Machigatta/wshbr-wordpress-themoviedb-sidebar",
            "downloads": []
        },
        {
            "name": "wshbr-share-to-discord",
            "cType": 3,
            "shortcut": "wshbrSTD",
            "type": "Wordpress Plugin",
            "version": "1.1",
            "last_update": "17.03.2019",
            "description": "A simple wordpress plugin to share your posts with your discord-servers.",
            "repo_link": "https://github.com/Machigatta/wshbr-wordpress-share-to-discord",
            "downloads": []
        },
        {
            "name": "wshbr-review",
            "cType": 3,
            "shortcut": "wshbrReview",
            "type": "Wordpress Plugin",
            "version": "2.0",
            "last_update": "12.03.2019",
            "description": "A wordpress plugin to hook a simple review form to your posts",
            "repo_link": "https://github.com/Machigatta/wshbr-wordpress-review",
            "downloads": []
        },
        {
            "name": "wshbr-spoiler",
            "cType": 3,
            "shortcut": "wshbrSpoiler",
            "type": "Wordpress Plugin",
            "version": "1.1",
            "last_update": "12.03.2019",
            "description": "A Wordpress-Plugin to add a \"Spoiler\" overlay on thumbnails",
            "repo_link": "https://github.com/Machigatta/wshbr-wordpress-spoiler",
            "downloads": []
        },
        {
            "name": "wshbr-featured-slider",
            "cType": 3,
            "shortcut": "wshbrFSlider",
            "type": "Wordpress Plugin",
            "version": "1.0",
            "last_update": "28.02.2019",
            "description": "A simple wordpress plugin to hook a picture to your posts and use it on a configurable slider in your Theme.",
            "repo_link": "https://github.com/Machigatta/wshbr-wordpress-featured-slider",
            "downloads": []
        },
        {
            "name": "discourse-humble-box",
            "cType": 3,
            "shortcut": "dckokoroHUMBLEbox",
            "type": "Discourse Plugin",
            "version": "1.0",
            "last_update": "23.03.2019",
            "description": "This plugin for Discourse uses the discourse-api to decorate the cooked-posts. Primary usage is for properly embedding Humblebundle.com-Links in Discourse posts and parsing them into better looking iframes.",
            "repo_link": "https://github.com/kokoro-ko/discourse-humble-box",
            "downloads": []
        },
        {
            "name": "discourse-anime-manga-box",
            "cType": 3,
            "shortcut": "dckokoroAMbox",
            "type": "Discourse Plugin",
            "version": "1.0",
            "last_update": "07.10.2017",
            "description": "This plugin for Discourse uses the discourse-api to decorate the cooked-posts. Primary usage is for properly embedding Anime- and Manga-Links in Discourse posts and parsing them into better looking iframes. ",
            "repo_link": "https://github.com/kokoro-ko/discourse-kokoro-box",
            "downloads": []
        },
        {
            "name": "discourse-onebox-endpoint",
            "cType": 3,
            "shortcut": "dckokoroEndpoint",
            "type": "PHP View",
            "version": "1.0",
            "last_update": "23.03.2019",
            "description": "Endpoints for 'discourse-humble-box' and 'discourse-anime-manga-box'.",
            "repo_link": "https://github.com/kokoro-ko/onebox-endpoint",
            "downloads": []
        },
        {
            "name": "psn-store-scraper",
            "cType": 3,
            "shortcut": "npmPSNStoreScraper",
            "type": "Node-Package",
            "version": "1.0.1",
            "last_update": "07.05.2019",
            "description": "Retrieve meta-data from the PlayStation-Network store for Objects (Games, DLCs etc)",
            "repo_link": "https://github.com/Machigatta/psn-store-scraper",
            "downloads": []
        }
    ]
}